apheris_auth/__init__.py
apheris_auth/config.py
apheris_auth/remote_data.py
apheris_auth/core/__init__.py
apheris_auth/core/api.py
apheris_auth/core/auth.py
apheris_auth/core/auth_helpers.py
apheris_auth/core/exceptions.py
apheris_auth/core/log.py
apheris_auth/core/m2m.py
apheris_auth/core/node_auth.py
apheris_auth/core/resource_owner_grant.py
apheris_auth/core/session.py
apheris_auth/core/sso_auth.py
apheris_auth/core/sso_helper.py
apheris_auth/external/__init__.py
apheris_auth/external/requests_auth/__init__.py
apheris_auth/external/requests_auth/errors.py
apheris_auth/external/requests_auth/oauth2_authentication_responses_server.py
apheris_auth-0.22.0.data/data/requirements.txt
apheris_auth-0.22.0.dist-info/licenses/LICENSE
apheris_auth-0.22.0.dist-info/METADATA
apheris_auth-0.22.0.dist-info/WHEEL
apheris_auth-0.22.0.dist-info/top_level.txt
apheris_auth-0.22.0.dist-info/RECORD
