Metadata-Version: 2.4
Name: apheris-auth
Version: 0.22.0
Summary: Apheris package to handle authentication and authorisation.
Author: Apheris
Keywords: python,apheris,federated learning
License-File: LICENSE
Requires-Dist: authlib==1.6.6
Requires-Dist: pydantic==2.12.5
Requires-Dist: PyJWT==2.10.*
Requires-Dist: python-dotenv==1.2.1
Requires-Dist: requests==2.32.5
Requires-Dist: requests-oauthlib==2.0.0
Requires-Dist: rich==14.2.0
Requires-Dist: structlog==25.5.0
Requires-Dist: termcolor==3.3.0
Dynamic: author
Dynamic: description
Dynamic: keywords
Dynamic: license-file
Dynamic: requires-dist
Dynamic: summary
